odoo/addons/l10n_ar_partner/README.rst
odoo/addons/l10n_ar_partner/__init__.py
odoo/addons/l10n_ar_partner/__manifest__.py
odoo/addons/l10n_ar_partner/i18n/es_AR.po
odoo/addons/l10n_ar_partner/i18n/l10n_ar_partner.pot
odoo/addons/l10n_ar_partner/models/__init__.py
odoo/addons/l10n_ar_partner/models/res_partner.py
odoo/addons/l10n_ar_partner/readme/CONTRIBUTORS.rst
odoo/addons/l10n_ar_partner/readme/DESCRIPTION.rst
odoo/addons/l10n_ar_partner/readme/HISTORY.rst
odoo/addons/l10n_ar_partner/readme/ROADMAP.rst
odoo/addons/l10n_ar_partner/static/description/icon.png
odoo/addons/l10n_ar_partner/static/description/index.html
odoo/addons/l10n_ar_partner/views/res_partner.xml
odoo14_addon_l10n_ar_partner-14.0.0.0.2.dist-info/METADATA
odoo14_addon_l10n_ar_partner-14.0.0.0.2.dist-info/WHEEL
odoo14_addon_l10n_ar_partner-14.0.0.0.2.dist-info/top_level.txt
odoo14_addon_l10n_ar_partner-14.0.0.0.2.dist-info/RECORD
