Metadata-Version: 2.1
Name: odoo14-addon-l10n-ar-partner
Version: 14.0.0.0.2
Summary: Extra Partner Data and Padrón for Argentina
Home-page: https://github.com/OCA/l10n-argentina
Author: Odoo Community Association (OCA), Codize, Exemax
Author-email: support@odoo-community.org
License: AGPL-3
Platform: UNKNOWN
Classifier: Programming Language :: Python
Classifier: Framework :: Odoo
Classifier: Framework :: Odoo :: 14.0
Classifier: License :: OSI Approved :: GNU Affero General Public License v3
Requires-Python: >=3.6
Requires-Dist: odoo14-addon-l10n-ar-afipws
Requires-Dist: odoo (<14.1dev,>=14.0a)
